{
  "id": "linux-q112",
  "name": "iostat 磁盘 I/O 分析",
  "domain": "linux",
  "description": "通过 iostat 真实输出数据，解读各字段含义，定位磁盘 I/O 瓶颈并给出处置方向",
  "version": "1.0.0",
  "questions": [
    {
      "id": "linux-q112",
      "domain": "linux",
      "type": "real-data",
      "difficulty": 2,
      "tags": ["iostat", "磁盘I/O", "性能分析", "sysstat", "iowait", "瓶颈定位"],
      "title": "iostat 如何分析磁盘 I/O 瓶颈？",
      "content": "某电商公司数据库服务器（Ubuntu 22.04，MySQL 8.0，8 核 CPU，64 GB 内存，单块 SATA HDD 2 TB）在大促期间出现严重的查询性能下降。DBA 反馈慢查询日志里大量 SELECT 语句耗时超过 5 秒，但 EXPLAIN 显示索引都在正常走，CPU 使用率只有约 55%。\n\n你 SSH 上机器后，执行 `iostat -x -k 1 3` 得到以下三次采样（第一次为开机以来的均值，后两次为实时数据，此处展示第三次）：\n\n```\n$ iostat -x -k 1 3\nLinux 5.15.0-89-generic (db-prod-01)   03/15/2024   _x86_64_   (8 CPU)\n\navg-cpu:  %user   %nice %system %iowait  %steal   %idle\n           8.23    0.00    4.17   41.35    0.00   46.25\n\nDevice       r/s     w/s    rkB/s     wkB/s  rrqm/s  wrqm/s  %rrqm  %wrqm  r_await  w_await  aqu-sz  rareq-sz  wareq-sz  svctm  %util\nsda         2.00  410.00    96.00  13120.00    0.00  318.00   0.00  43.66     8.40   126.82   51.87     48.00     32.00   2.39  99.10\nsdb         0.00    2.50     0.00     40.00    0.00    0.50   0.00  16.67     0.00     1.20    0.00      0.00     16.00   0.40   0.10\n```\n\n请根据这份 iostat 输出，逐字段分析各项指标的含义，判断当前磁盘 I/O 的健康状况，指出瓶颈所在，并说明你的完整判断依据和下一步排查方向。",
      "answer": "## iostat 是什么，从哪里来\n\niostast 是 Linux 上 **sysstat** 工具集的一部分，全称 Input/Output Statistics，专门用来统计 CPU 使用率与块设备（磁盘、分区、LVM 卷等）的 I/O 吞吐和延迟指标。它本质上读取的是内核在 `/proc/diskstats` 暴露的数据，每隔指定间隔采样一次，因此可以做实时监控。安装很简单：`apt install sysstat` 或 `yum install sysstat`，安装后即可使用 `iostat` 命令。\n\n日常诊断时最常用的命令格式是 `iostat -x -k 1 10`：`-x` 表示开启扩展统计（没有这个参数你只能看到非常有限的信息）；`-k` 让吞吐量以 KB/s 为单位而非默认的块数，更直观；`1` 是采样间隔秒数；`10` 是采样次数。**特别注意：第一次输出永远是从开机到现在的累计均值，不代表当前状态，做实时诊断时直接跳过第一次输出，看第二次及以后。**\n\n## 先看 CPU 区域：%iowait 是第一个报警信号\n\n很多工程师拿到 iostat 输出后直接跳到设备区域，其实 CPU 区域的 `%iowait` 才是最快速的全局判断指标。`%iowait` 的准确定义是：至少有一个未完成的 I/O 请求时，CPU 处于空闲状态的时间占比。说人话就是——CPU 没有可执行的任务，正站在那里等磁盘。\n\n这份输出里 `%iowait = 41.35%`，CPU 有超过四成的时间在空等 I/O。生产环境的经验阈值：`%iowait > 5%` 值得关注，`> 20%` 需要立刻排查，`> 40%` 说明 I/O 已经严重拖慢了整个系统。这也解释了为什么 DBA 看 CPU 使用率只有 55%——另外 41% 其实是 iowait，那颗 CPU 核心并不是在「工作」，而是在「发呆」。\n\n## 逐字段解读设备区域\n\n确认 I/O 是问题后，再来看设备行。sda 和 sdb 对比极为鲜明，问题显然在 sda 上。下面逐字段拆解 sda 的数据。\n\n**r/s 和 w/s** 分别是每秒完成的读请求数和写请求数。sda 是 `2.00` 读、`410.00` 写，这是一个典型的**写密集型**负载——MySQL 的 InnoDB redo log、binary log、数据页刷写全部压在这块盘上。每秒 410 次写请求对一块 SATA HDD 而言已经相当重。\n\n**rkB/s 和 wkB/s** 是读写吞吐量，单位 KB/s。`96 + 13120 ≈ 13 MB/s` 的总吞吐量看起来不大，SATA HDD 理论顺序写可以达到 150 MB/s。为什么 13 MB/s 就把盘打满了？答案在后面的 `aqu-sz` 和 `w_await` 里。\n\n**rrqm/s 和 wrqm/s** 是每秒被合并的读写请求数，`wrqm/s = 318.00` 说明内核的 I/O 调度器（elevator）每秒把 318 个写请求合并了——也就是说实际发给磁盘的写请求远少于应用层发出的。`%wrqm = 43.66%` 表示有 44% 的写请求被合并掉了。合并本是好事，但合并如此之多说明请求积压严重、队列里有大量可合并的相邻请求，内核在拼命「帮忙」也追不上写入速度。\n\n**r_await 和 w_await** 是每次 I/O 请求从发出到完成的平均等待时间，单位毫秒。这是**最直观的延迟指标**。`r_await = 8.40 ms` 勉强在 HDD 的正常范围内（HDD 随机读寻道时间约 5-10 ms），但 `w_await = 126.82 ms`——写请求平均要等 127 毫秒才能完成。InnoDB 的事务提交要等 redo log 落盘，127 ms 的写延迟直接变成了事务提交的延迟，再叠加查询本身的执行时间，慢查询超 5 秒完全说得通。\n\n**aqu-sz**（Average Queue Size，平均队列深度）是整个输出里**最重要的饱和度指标**。它反映的是在观测时间窗口内，磁盘 I/O 队列里平均有多少请求在排队等待。`aqu-sz = 51.87`，也就是说盘在任何一个瞬间平均有 52 个请求在排队。一块健康的 HDD 其 `aqu-sz` 应该接近 0，偶尔到 1-2 就算有压力了，达到 52 意味着磁盘已经处于极度饱和的状态。\n\n**svctm**（Service Time）是磁盘实际服务一个请求所需的时间（已废弃但仍可参考）。`svctm = 2.39 ms` 说明磁盘本身的服务能力还在——它服务一个请求只需 2.4 ms。而 `w_await = 126.82 ms`，两者相差 124 ms，这 124 ms 全部是**排队等待时间**。用 `w_await / svctm ≈ 53` 可以粗估平均每个请求要等前面 53 个请求先完成才能被处理，和 `aqu-sz = 51.87` 高度吻合，互相印证。\n\n**%util** 是磁盘在采样周期内处于忙碌状态的时间占比。`sda %util = 99.10%`，这块盘 99% 的时间都在处理 I/O，几乎没有空闲。对 HDD 而言，`%util > 80%` 就应该警惕，99% 基本宣告了磁盘已经饱和。\n\n## 综合判断：三重信号同时指向 sda 饱和\n\n拿到这份输出，我会按这个顺序下结论：第一，`%iowait = 41%` 确认 I/O 是全局瓶颈；第二，`%util = 99%` 确认 sda 已经饱和；第三，`aqu-sz = 51.87` 与 `w_await = 127 ms` 确认是**队列积压导致的排队延迟**，而非磁盘硬件故障（svctm 仍正常）。三个信号同时出现，诊断非常明确：这块 SATA HDD 已经无法应对 MySQL 大促期间的写入压力。\n\n## 为什么对 SSD 不能用同一套阈值\n\n这里有个关键认知要纠正：`%util 100%` 对 HDD 意味着饱和，但对 SSD（尤其是 NVMe）未必。现代 NVMe SSD 支持多队列（NVMe 规范支持最多 65535 个队列，每队列 65535 个条目），内核的 `%util` 计算模型仍然是基于「单队列」假设的时间占比，无法反映多队列 SSD 的真实利用率。判断 NVMe SSD 瓶颈要优先看 `r_await`、`w_await` 是否超过 SSD 的标定延迟（通常 < 0.1 ms），以及 `aqu-sz` 是否持续走高，而不是 `%util`。\n\n## 下一步：找到是哪个进程在写\n\n确认 sda 饱和后，下一步是定位到具体进程。`iotop -o -b -n 3` 可以实时显示正在产生 I/O 的进程列表；`lsof +D /var/lib/mysql` 可以看到 MySQL 打开的文件列表。结合 MySQL 的 `SHOW ENGINE INNODB STATUS` 里的 `LOG` 和 `BUFFER POOL AND MEMORY` 段，可以判断是 redo log 刷写、data page checkpoint 还是 binlog 写入在主导。常见的临时缓解手段包括调整 `innodb_io_capacity`（让 InnoDB 更激进地批量刷写而不是小批量频繁刷）、确认 `innodb_flush_log_at_trx_commit` 的设置，以及将 binlog 目录挪到单独的磁盘。根本解决方案是换 SSD——SATA HDD 在 OLTP 写密集场景下的随机 I/O 能力已经是硬上限，调参无法突破物理瓶颈。\n\n## 生产监控建议\n\n在 Prometheus + node_exporter 的监控体系里，对应的指标是 `node_disk_io_time_seconds_total`（换算成 %util）、`node_disk_read_time_seconds_total / node_disk_reads_completed_total`（r_await）和 `node_disk_write_time_seconds_total / node_disk_writes_completed_total`（w_await）。建议对 HDD 设置告警规则：`%util > 70%` 发警告，`aqu-sz > 5` 发告警，`w_await > 30 ms` 持续 2 分钟发 PagerDuty。这样能在用户感知到慢查询之前就介入处理。",
      "keyPoints": [
        "iostat 是 sysstat 工具集的一员，读取 /proc/diskstats 数据；使用时必须加 -x 参数才能看到 await、aqu-sz 等关键扩展字段，否则只有基础吞吐量信息",
        "%iowait 是 CPU 区域最关键的全局信号，表示 CPU 因等待 I/O 而空闲的时间占比，超过 20% 需要立刻排查，41% 说明 I/O 已严重拖慢整个系统",
        "aqu-sz（平均队列深度）是判断磁盘饱和度最可靠的指标，HDD 的健康值接近 0，aqu-sz = 51 说明极度饱和，有大量请求在排队等候",
        "w_await 远大于 svctm 时，差值就是排队等待时间，本例中 127ms - 2.4ms ≈ 125ms 的队列延迟直接转化为 MySQL 事务提交延迟，是慢查询的根本原因",
        "%util 对 HDD 有效：99% 代表饱和；但对 NVMe SSD 不适用，因为多队列架构下 %util 无法准确反映利用率，应改看 await 和 aqu-sz",
        "wrqm/s 很高说明内核 I/O 调度器在大量合并写请求，这是磁盘追不上写入速度的间接信号，应与 aqu-sz 结合判断",
        "iostat 的第一行输出是从开机到现在的累计均值，做实时诊断时必须忽略第一次输出，从第二次采样开始才是当前状态",
        "定位到磁盘饱和后，用 iotop -o 找到具体进程，再结合 SHOW ENGINE INNODB STATUS 判断是 redo log、binlog 还是数据页 checkpoint 在主导写入"
      ],
      "quiz": [
        {
          "id": "linux-q112-quiz-1",
          "question": "在上面的 iostat 输出中，sda 的 %util = 99.10%，这说明了什么？",
          "choices": [
            {"id": "A", "text": "这块 HDD 在采样周期内几乎一直处于忙碌状态，已达到饱和，无法再接受更多 I/O 请求而不产生排队"},
            {"id": "B", "text": "该磁盘的 CPU 占用率达到 99%，说明磁盘控制器 CPU 资源耗尽"},
            {"id": "C", "text": "磁盘的读写缓存命中率只有 0.9%，缓存几乎完全失效"},
            {"id": "D", "text": "磁盘传输效率为 99.1%，表明磁盘工作状态非常良好，接近满载但健康"}
          ],
          "correctAnswer": "A",
          "explanation": "%util 的定义是在采样时间窗口内，设备处于忙碌（有 I/O 请求在处理）状态的时间比例。对于 HDD 这种单队列设备，%util 接近 100% 意味着磁盘已经饱和，几乎没有空闲时间处理新请求，新来的请求只能在内核 I/O 队列中等待，从而造成 aqu-sz 和 await 飙升。B 选项混淆了磁盘设备和 CPU 的概念；C 选项是对字段的错误臆想；D 选项的理解是反向的——%util 高对 HDD 意味着饱和而非「良好」，健康的磁盘应该有足够的空闲时间消化突发请求。"
        },
        {
          "id": "linux-q112-quiz-2",
          "question": "iostat -x 输出中的 aqu-sz 字段含义是什么？",
          "choices": [
            {"id": "A", "text": "磁盘在采样周期内的平均 I/O 队列深度，即任意时刻平均有多少个 I/O 请求在等待被磁盘处理"},
            {"id": "B", "text": "磁盘的最大队列容量（硬件层面支持的最大并发请求数）"},
            {"id": "C", "text": "每次 I/O 请求的平均数据块大小（以扇区为单位）"},
            {"id": "D", "text": "磁盘驱动队列满导致丢弃的请求数量"}
          ],
          "correctAnswer": "A",
          "explanation": "aqu-sz（Average Queue Size）是利用利特尔定律（Little's Law）从 /proc/diskstats 的 time_in_queue 字段推导出来的平均队列深度。它反映的是在观测时间窗口内，内核 I/O 队列中平均同时排队的请求数量。一块健康的 HDD 的 aqu-sz 应接近 0 到 1，超过 2 就开始值得关注，而本题的 51.87 代表极度饱和。B 选项描述的是硬件队列深度（nr_requests），是个不同的概念；C 选项描述的是 rareq-sz/wareq-sz 字段；D 选项是对 iostat 字段的错误理解，iostat 不统计丢弃请求。"
        },
        {
          "id": "linux-q112-quiz-3",
          "question": "sda 的 w_await = 126.82 ms，而 svctm = 2.39 ms，两者差距悬殊说明了什么？",
          "choices": [
            {"id": "A", "text": "磁盘硬件存在故障，实际服务能力严重下降，需要立即更换"},
            {"id": "B", "text": "大约 124 ms 的时间花在了 I/O 队列中排队等待，磁盘本身的服务能力正常，但请求积压导致了极高的端到端延迟"},
            {"id": "C", "text": "写请求的平均大小比读请求大 53 倍，导致写入时间更长"},
            {"id": "D", "text": "w_await 和 svctm 的差值代表操作系统内核处理中断的时间，属于内核调度问题"}
          ],
          "correctAnswer": "B",
          "explanation": "await = 排队等待时间 + svctm（磁盘实际服务时间）。svctm = 2.39 ms 说明这块磁盘的硬件本身响应时间正常，每个请求一旦被服务只需 2.4 ms。而 w_await = 126.82 ms，说明请求在被磁盘接手之前，光是在内核 I/O 队列里就等了约 124 ms。w_await / svctm ≈ 53 可以粗估平均每个请求前面还有约 53 个请求在排队，与 aqu-sz = 51.87 高度吻合。这是一个「磁盘没坏，但追不上写入速度」的典型模式，不能通过替换磁盘解决，需要减少写入量或升级到更高 IOPS 的存储。"
        },
        {
          "id": "linux-q112-quiz-4",
          "question": "执行 `iostat -x -k 1 5` 时，为什么诊断时应该忽略第一次输出？",
          "choices": [
            {"id": "A", "text": "第一次采样数据是随机噪声，统计误差最大"},
            {"id": "B", "text": "第一次输出显示的是从系统启动到现在的累计平均值，而不是当前 1 秒内的实时数据，无法反映当下的 I/O 状态"},
            {"id": "C", "text": "iostat 初始化时需要预热，第一次采样 CPU 占用高，会干扰磁盘数据"},
            {"id": "D", "text": "第一次输出只包含 CPU 信息，没有设备行数据"}
          ],
          "correctAnswer": "B",
          "explanation": "iostat 的工作原理是读取 /proc/diskstats 中的累计计数器，然后用两次采样的差值除以时间间隔得到速率。第一次输出没有「上一次」可以对比，因此直接用从内核启动到现在的累计值除以系统运行时间，得到的是全生命周期的均值。如果系统刚经历了一次 I/O 风暴然后恢复正常，第一次输出会显示很高的均值，误导判断；反之如果系统大部分时间空闲只有最近几秒繁忙，第一次输出会低估当前状态。做实时诊断必须从第二次输出开始读。"
        },
        {
          "id": "linux-q112-quiz-5",
          "question": "avg-cpu 区域的 %iowait = 41.35% 意味着什么？",
          "choices": [
            {"id": "A", "text": "CPU 正在将 41.35% 的算力用于处理 I/O 中断和 DMA 传输，是 I/O 占用了 CPU 资源"},
            {"id": "B", "text": "CPU 有 41.35% 的时间处于空闲但有未完成 I/O 请求的状态，说明 I/O 成为了整个系统的瓶颈"},
            {"id": "C", "text": "有 41.35% 的 I/O 请求超时未完成，I/O 错误率极高"},
            {"id": "D", "text": "%iowait 是磁盘 I/O 带宽利用率，41.35% 说明磁盘还有近 60% 的带宽可以利用"}
          ],
          "correctAnswer": "B",
          "explanation": "%iowait 的准确定义是：在统计周期内，至少存在一个未完成的 I/O 请求的情况下，CPU 处于空闲（idle）状态的时间占比。它不代表 CPU 在「做」I/O 相关的工作，恰恰相反，CPU 此时什么都做不了，只能等磁盘返回数据。%iowait 高说明 I/O 延迟已经高到让 CPU 都没事干，进而造成任务调度饥饿。生产经验：%iowait > 20% 就需要排查 I/O 子系统，> 40% 说明 I/O 瓶颈已经在显著拖慢系统整体吞吐。A 选项混淆了概念，I/O 中断处理是 %sys 的一部分而不是 %iowait。"
        },
        {
          "id": "linux-q112-quiz-6",
          "question": "对于 NVMe SSD，以下哪种说法是正确的？",
          "choices": [
            {"id": "A", "text": "NVMe SSD 的 %util 阈值和 HDD 相同，超过 80% 就说明饱和"},
            {"id": "B", "text": "NVMe SSD 不会出现 I/O 瓶颈，不需要用 iostat 监控"},
            {"id": "C", "text": "NVMe SSD 支持多队列，%util 基于单队列时间模型计算，可能在 %util 很高时仍未饱和；应优先看 await 是否超过标定延迟以及 aqu-sz 的趋势"},
            {"id": "D", "text": "NVMe SSD 的 aqu-sz 应该为 0，任何大于 0 的值都说明存在瓶颈"}
          ],
          "correctAnswer": "C",
          "explanation": "Linux 内核的 %util 计算逻辑来自传统的单队列块设备模型：采样周期内设备有 I/O 请求在处理的时间 / 总时间。NVMe 设备支持多命令队列（Multi-Queue，MQ），理论上可以同时处理来自多个队列的大量并发请求，单队列时间模型会严重低估设备的实际并发能力，也会导致 %util 「虚高」。因此对 NVMe SSD，更可靠的判断方式是：看 r_await 和 w_await 是否超过该型号 SSD 的标定延迟（通常 < 0.1 ms），以及 aqu-sz 是否持续增长。NVMe SSD 的合理 aqu-sz 可以相对较高，这是正常利用多队列并发的表现。"
        },
        {
          "id": "linux-q112-quiz-7",
          "question": "iostat 输出中 wrqm/s = 318 且 %wrqm = 43.66%，这说明了什么？",
          "choices": [
            {"id": "A", "text": "每秒有 318 次写请求因为错误被内核丢弃，磁盘存在硬件问题"},
            {"id": "B", "text": "内核 I/O 调度器每秒合并了 318 次写请求，意味着应用层发出的写请求远多于 w/s 显示的 410 次，合并是队列压力大的侧面信号"},
            {"id": "C", "text": "磁盘的写缓存命中率为 43.66%，缓存效果一般"},
            {"id": "D", "text": "每秒有 43.66% 的写请求使用了 Direct I/O，绕过了 page cache"}
          ],
          "correctAnswer": "B",
          "explanation": "rrqm/s 和 wrqm/s 是内核 I/O 调度器（scheduler/elevator）在将请求发送给驱动之前，将相邻 LBA 地址的请求合并成更大请求的次数。%wrqm = wrqm / (wrqm + w) = 43.66% 说明实际应用发出的写 I/O 请求数大约是 410 + 318 = 728 次/秒，但经过合并后只有 410 次到达磁盘驱动层。高 wrqm 一方面说明写请求的空间局部性尚可（地址相邻才能合并），另一方面说明队列里有大量请求堆积等待合并——这是磁盘追不上写速度的侧面信号，应与 aqu-sz 和 %util 一起解读。"
        },
        {
          "id": "linux-q112-quiz-8",
          "question": "在生产环境中，如何用 iostat 配合其他工具快速定位是哪个进程在导致磁盘 I/O 饱和？",
          "choices": [
            {"id": "A", "text": "iostat 本身可以直接显示每个进程的 I/O 量，在 -x 模式下加 -p 参数即可按进程展示"},
            {"id": "B", "text": "用 iotop -o 找到正在产生 I/O 的进程，再配合 lsof -p <pid> 确认该进程在操作哪些文件"},
            {"id": "C", "text": "重启所有服务，观察重启后哪个服务让 %util 再次升高，即为元凶"},
            {"id": "D", "text": "只能通过 strace -e trace=write -p <pid> 逐一附加到进程来判断，没有更高效的方法"}
          ],
          "correctAnswer": "B",
          "explanation": "iostat 是设备级别的统计工具，它不知道哪个进程产生了 I/O，只能告诉你某块磁盘的整体状态。要定位进程，标准组合是：① iotop -o -b -n 3（-o 只显示有 I/O 的进程，-b 批处理模式便于重定向）快速找到 I/O 大户；② lsof -p <pid> 或 lsof +D /mount/point 确认该进程在读写哪些文件；③ 如果是数据库，进一步用 SHOW ENGINE INNODB STATUS 或 pg_stat_bgwriter 等数据库内置视图判断具体是什么操作。A 选项是错误的，iostat 没有按进程展示的能力；C 选项代价太大且不准确；D 选项的 strace 开销极高且只能串行附加，不适合生产快速排查。"
        },
        {
          "id": "linux-q112-quiz-9",
          "question": "以下哪个组合能最准确地判断一块 HDD 已经出现 I/O 饱和？",
          "choices": [
            {"id": "A", "text": "%util > 50% 且 r/s + w/s > 200"},
            {"id": "B", "text": "rkB/s + wkB/s 超过 HDD 标定顺序读写带宽的 50%"},
            {"id": "C", "text": "%util > 80% 且 aqu-sz 持续大于 1，同时 w_await 或 r_await 明显超过磁盘正常寻道时间（HDD 约 5-15 ms）"},
            {"id": "D", "text": "svctm > 10 ms 且 %util > 30%"}
          ],
          "correctAnswer": "C",
          "explanation": "判断 HDD 饱和需要多个指标共同印证。%util > 80% 是第一道门槛，说明盘的时间利用率已经很高；aqu-sz 持续 > 1 说明请求开始积压，已有请求需要排队；await 超过正常寻道时间说明延迟已经可观测地恶化。三者同时成立才能确认饱和而非短暂波动。单独看 r/s + w/s（A 选项）不够，因为大块顺序 I/O 的吞吐量高但 IOPS 低，不会导致饱和；带宽占比（B 选项）对随机小 I/O 无效，因为 HDD 瓶颈通常是寻道时间而非带宽；svctm（D 选项）在新内核中已标记为弃用且计算不准确，不应作为主要依据。"
        },
        {
          "id": "linux-q112-quiz-10",
          "question": "监控告警发现某台服务器的磁盘 %util 持续在 95% 以上，但 aqu-sz 始终接近 0，await 也正常。这种情况最可能的原因是？",
          "choices": [
            {"id": "A", "text": "磁盘即将损坏，%util 高而 aqu-sz 低是硬件早期故障的典型表现"},
            {"id": "B", "text": "这是 NVMe SSD 的正常表现，多队列下 %util 计算偏高，实际并未饱和；或者是顺序 I/O 在高效地把磁盘打满但延迟仍在正常范围内"},
            {"id": "C", "text": "iostat 数据采集存在 bug，数值不可信，应切换到 sar 工具"},
            {"id": "D", "text": "%util 高且 aqu-sz 低是不可能同时出现的，一定是采样间隔太长导致的统计误差"}
          ],
          "correctAnswer": "B",
          "explanation": "这种看似矛盾的情况在两种场景下是正常的。第一种：NVMe SSD，由于多队列机制，%util 的时间模型会虚高，设备实际上仍有并发处理能力，aqu-sz 低和 await 正常是真实健康的信号；第二种：HDD 或 SATA SSD 上的大块顺序 I/O（比如数据库备份、日志归档），磁盘以接近满带宽在写，每个请求都能很快被处理（svctm 低、await 低），aqu-sz 自然接近 0，但 %util 接近 100% 是因为请求一直不断。这种情况下 %util 高并不代表有问题，只要 await 和 aqu-sz 正常，系统就是健康的。告警规则应该同时包含 await 条件，而不只是 %util。"
        }
      ],
      "references": [
        {
          "title": "Linux man page: iostat(1) — sysstat",
          "url": "https://man7.org/linux/man-pages/man1/iostat.1.html"
        },
        {
          "title": "Brendan Gregg — Linux Disk I/O Performance Analysis",
          "url": "https://www.brendangregg.com/linuxperf.html"
        },
        {
          "title": "kernel.org — Block I/O statistics in /proc/diskstats",
          "url": "https://www.kernel.org/doc/Documentation/ABI/testing/procfs-diskstats"
        }
      ]
    }
  ]
}
