{
  "id": "monitoring-q61",
  "name": "Sidecar 模式 vs DaemonSet 模式收集容器日志的优缺点",
  "domain": "monitoring",
  "description": "对比 Kubernetes 中两种主流容器日志收集架构的设计取舍、适用场景与生产实践",
  "version": "1.0.0",
  "questions": [
    {
      "id": "monitoring-q61",
      "domain": "monitoring",
      "type": "comparison",
      "difficulty": 2,
      "tags": ["kubernetes", "logging", "daemonset", "sidecar", "fluent-bit", "fluentd", "observability"],
      "title": "Sidecar 模式 vs DaemonSet 模式收集容器日志，各有什么优缺点？",
      "content": "在 Kubernetes 集群中，日志收集是每个运维团队都绕不过的基础问题。容器的无状态性决定了一旦 Pod 被销毁，容器内的文件系统就随之消失，日志必须在 Pod 消亡之前被可靠地采集并发送到外部存储系统（Elasticsearch、Loki、对象存储等）。\n\n为此，社区形成了两种主流的日志收集架构：**DaemonSet 模式**和 **Sidecar 模式**。两种方案都经过了大规模生产验证，但在资源消耗、隔离性、配置灵活性和运维复杂度上各有取舍。\n\n面试中考察这道题，不只是想听你说「DaemonSet 是一个节点一个 Agent」，而是想看你有没有在真实集群中做过日志方案选型，能不能说清楚什么场景该用哪种，以及各自的边界条件在哪里。\n\n以下是一个具体的场景：你所在的团队维护一个 200 节点的 Kubernetes 集群，运行着 60 多个微服务。其中大部分服务已经改造为将日志输出到 stdout，但有几个遗留的 Java 服务（Spring Boot + Logback 配置）仍然将日志写入容器内 `/app/logs/application.log` 文件，同时你们还承接了来自另外两个业务部门的工作负载，他们要求日志数据在采集层就必须物理隔离，不能共享同一个 Agent 进程。\n\n在这个场景下，你会如何设计日志收集方案？DaemonSet 和 Sidecar 分别应该承担什么角色？它们各自的资源消耗差距大概是多少个量级？",
      "answer": "## 理解 Kubernetes 日志的底层流向\n\n要真正搞清楚 DaemonSet 和 Sidecar 的区别，必须先理解容器日志在 Kubernetes 中是怎么流动的。很多人以为日志是「自动被 K8s 收集的」，实际上并不是这样。Kubernetes 本身不负责日志收集，它只负责把容器的 stdout/stderr 通过容器运行时（containerd 或 CRI-O）重定向到宿主机的文件系统中。\n\n具体来说，当一个 Pod 启动后，kubelet 通知容器运行时创建容器，容器运行时将该容器的 stdout/stderr 落盘到 `/var/log/pods/<namespace>_<pod-name>_<pod-uid>/<container-name>/0.log` 路径下。同时，`/var/log/containers/` 目录下会有对应的符号链接指向这些文件，链接名格式为 `<pod-name>_<namespace>_<container-name>-<container-id>.log`。这个路径约定是 Kubernetes 社区的事实标准，Fluent Bit、Fluentd、Filebeat、Vector 等主流日志 Agent 都默认从这里读取。\n\n你可以在任意节点上执行 `ls -la /var/log/containers/` 验证这一点，输出大概是这样：\n\n```\nlrwxrwxrwx 1 root root  86 Jan 15 10:23 nginx-7d9f8b-xxx_default_nginx-abc123.log\n  -> /var/log/pods/default_nginx-7d9f8b-xxx_uid/nginx/0.log\nlrwxrwxrwx 1 root root  98 Jan 15 10:24 fluentbit-yyy_kube-system_fluent-bit-def456.log\n  -> /var/log/pods/kube-system_fluentbit-yyy_uid/fluent-bit/0.log\n```\n\n理解了这个文件布局之后，DaemonSet 模式的工作原理就非常清晰了：在每个节点上运行一个日志 Agent Pod，把宿主机的 `/var/log/pods` 和 `/var/log/containers` 目录以 hostPath Volume 的形式挂载进去，Agent 就能读取这个节点上所有容器的日志。Sidecar 模式则完全不同——它不依赖宿主机文件系统，而是在业务 Pod 的 spec 中额外注入一个日志收集容器，业务容器和 Sidecar 容器共享同一个 Pod 的存储卷（通过 emptyDir 或 PVC），Sidecar 直接读取业务容器写入的日志文件。\n\n## DaemonSet 模式：简洁是它最大的优势\n\nDaemonSet 模式的核心逻辑是「一个节点，一个 Agent」。一个典型的 Fluent Bit DaemonSet 配置大概是这样的：\n\n```yaml\n# fluent-bit-daemonset.yaml\napiVersion: apps/v1\nkind: DaemonSet\nmetadata:\n  name: fluent-bit\n  namespace: kube-system\nspec:\n  selector:\n    matchLabels:\n      app: fluent-bit\n  template:\n    spec:\n      serviceAccountName: fluent-bit  # 需要 pods/log 的 get 权限\n      containers:\n      - name: fluent-bit\n        image: fluent/fluent-bit:2.2.2\n        resources:\n          requests:\n            cpu: 50m\n            memory: 64Mi\n          limits:\n            cpu: 200m\n            memory: 128Mi\n        volumeMounts:\n        - name: varlog\n          mountPath: /var/log           # 宿主机日志目录挂载进来\n        - name: varlibdockercontainers\n          mountPath: /var/lib/docker/containers\n          readOnly: true\n      volumes:\n      - name: varlog\n        hostPath:\n          path: /var/log\n      - name: varlibdockercontainers\n        hostPath:\n          path: /var/lib/docker/containers\n```\n\n这种架构的资源效率非常高。一个 200 节点的集群只需要 200 个 Fluent Bit 实例，每个实例内存在 20-30MB 左右，总计 200 × 30MB = 6GB。运维团队只需要维护一份 DaemonSet 配置，升级时滚动更新即可，整个方案的运维成本极低。\n\nDaemonSet 模式还有一个隐性优势是延迟低。Agent 直接在本地读取文件，不存在网络 hop，日志从写入到被 Agent 读取的延迟通常在 100ms 以内。\n\n但 DaemonSet 模式有一个根本性的限制：它只能收集写到 stdout/stderr 的日志。如果一个遗留 Java 服务用 Logback 把日志写进容器内的 `/app/logs/application.log` 文件，DaemonSet Agent 根本看不到这些文件——因为这些文件在容器的 overlay filesystem 里，宿主机挂载点无法访问到容器内部的写时复制层。另一个限制是隔离性：同一个 Agent 进程会读取该节点上所有 Pod 的日志，在多租户场景下这是一个潜在的安全隐患，如果 Agent 进程本身出现漏洞，理论上可以访问到所有租户的日志内容。\n\n## Sidecar 模式：灵活但代价明显\n\nSidecar 模式注入的是一个独立的日志收集容器，与业务容器通过共享 Volume 交换文件。以那个 Java 遗留服务为例，配置大概是这样的：\n\n```yaml\n# java-app-with-sidecar.yaml\napiVersion: v1\nkind: Pod\nspec:\n  containers:\n  - name: java-app\n    image: my-java-app:1.0.0\n    volumeMounts:\n    - name: log-volume\n      mountPath: /app/logs            # 业务容器把日志写到这里\n  - name: log-collector               # Sidecar 日志收集容器\n    image: fluent/fluent-bit:2.2.2\n    resources:\n      requests:\n        cpu: 50m\n        memory: 64Mi\n    volumeMounts:\n    - name: log-volume\n      mountPath: /app/logs            # 与业务容器共享同一个 Volume\n    - name: fluent-bit-config\n      mountPath: /fluent-bit/etc\n  volumes:\n  - name: log-volume\n    emptyDir: {}                      # 两个容器共享这块临时存储\n  - name: fluent-bit-config\n    configMap:\n      name: java-app-fluent-bit-config\n```\n\n这种方案解决了文件日志收集的问题，同时每个 Pod 可以拥有完全独立的 Fluent Bit 配置——不同的 Pod 可以把日志发送到不同的 Kafka Topic 或 Elasticsearch 索引，实现真正的数据隔离，满足多租户场景下的安全要求。\n\n资源代价是显而易见的。同样是 200 节点、每节点平均 20 个 Pod 的集群，如果全部采用 Sidecar 方案就需要 4000 个 Fluent Bit 实例。每个实例哪怕只申请 64Mi 内存，总计就是 4000 × 64MB = 256GB 内存专门用于日志收集，这已经是一个不容忽视的开销了。与 DaemonSet 方案的 ~6GB 相比，相差了将近 40 倍。加上 CPU 和 Pod 调度资源，Sidecar 方案在大规模集群中的成本可以轻松达到 DaemonSet 的 10-20 倍。\n\n还有一个经常被忽视的问题：Sidecar 容器和业务容器耦合在同一个 Pod 里，如果日志收集容器因 OOM 被 kubelet kill 掉，整个 Pod 都会被重启（除非你仔细设计了 restartPolicy），这对在线业务是不可接受的。在 Kubernetes 1.29 之前，Pod 级别的 Sidecar 生命周期管理一直是个痛点，社区有大量 issue 讨论这个问题。直到 Kubernetes 1.29 正式引入了 Sidecar Container 的 GA 特性，通过在 `initContainers` 中配置 `restartPolicy: Always`，才让 Sidecar 具备了真正独立于主容器的生命周期语义——Sidecar 可以在主容器退出后继续运行、排空日志缓冲区，然后再退出。\n\n## 生产实践：混合架构才是答案\n\n在实际生产环境中，纯 DaemonSet 或纯 Sidecar 都不是最优解。大多数成熟团队用的是混合架构：DaemonSet 处理主流路径，Sidecar 处理特殊情况。\n\n判断标准很简单：如果你的应用能输出到 stdout/stderr（这是 Kubernetes 官方推荐的做法，The Twelve-Factor App 方法论也明确要求将日志作为事件流输出到 stdout），就用 DaemonSet；如果它是遗留应用且短期内无法改造，或者业务方对日志隔离有强制要求，才引入 Sidecar。对于前面提到的那个 200 节点场景，合理的方案是：绝大多数微服务继续用 DaemonSet 模式的 Fluent Bit 收集 stdout 日志，只有那几个写文件的遗留 Java 服务和需要严格隔离的租户才注入 Sidecar。这样既控制了整体资源消耗，又解决了特殊需求。\n\n关于 Agent 的选型，Fluent Bit 在 DaemonSet 场景的首选地位已经相当稳固。相比 Fluentd，Fluent Bit 是 C 语言实现，内存占用通常在 5-30MB，而同等吞吐下 Fluentd（Ruby 实现）需要 100-300MB。如果集群规模比较小（50 节点以内），用 Fluentd 的 Ruby 生态和丰富插件也没什么问题；但超过 100 节点之后，Fluent Bit 的内存优势就会很明显地体现在账单上。\n\n最后一个值得注意的生产坑：当 DaemonSet Agent 落后于日志产生速度时（比如下游 Elasticsearch 出现性能抖动），宿主机的 `/var/log/pods` 目录会堆积大量日志文件，严重时会耗尽节点磁盘空间，触发 kubelet 的磁盘压力驱逐（`DiskPressure`），把完全健康的业务 Pod 赶走。Kubernetes 本身有 kubelet 的 log rotation 机制，由 `--container-log-max-size`（默认 10Mi）和 `--container-log-max-files`（默认 5）参数控制，但很多集群用的是默认值。生产环境中应该根据日志产生速率和节点磁盘容量显式设置这两个参数，并为日志目录配置单独的磁盘分区或监控告警，防止日志把系统盘写满。",
      "keyPoints": [
        "DaemonSet 模式每个节点只运行一个日志 Agent，通过 hostPath 挂载宿主机 `/var/log/containers` 和 `/var/log/pods` 目录统一收集所有 Pod 的 stdout/stderr，是 Kubernetes 官方推荐的默认日志收集方案，资源消耗低、运维成本小",
        "Sidecar 模式在每个 Pod 内注入一个日志收集容器，通过 emptyDir Volume 与业务容器共享文件系统，可以读取业务容器写入文件的日志，适合应用无法改造为标准输出、或需要 Pod 级别独立日志配置的场景",
        "DaemonSet 只能采集 stdout/stderr 日志，无法访问容器 overlay filesystem 内部的日志文件；Sidecar 可以读取容器内任意文件，但代价是资源消耗可达 DaemonSet 的 10-20 倍（100 节点 × 20 Pod 场景下约 40 倍内存差距）",
        "多租户场景或对日志安全隔离有强制要求时优先选 Sidecar，因为 DaemonSet 的单 Agent 进程会读取节点上所有 Pod 的日志，存在跨租户数据访问风险；Sidecar 天然具备 Pod 级别的进程隔离",
        "Kubernetes 1.29 正式 GA 的 Sidecar Container 特性（initContainers 配置 `restartPolicy: Always`）解决了长期存在的 Sidecar 生命周期问题，使 Sidecar 可以在主容器退出后继续排空日志缓冲再退出",
        "生产最佳实践是混合架构：DaemonSet 收集 stdout 日志（主流路径），Sidecar 仅用于遗留应用文件日志或有强隔离要求的租户，避免把 Sidecar 用在所有 Pod 上导致资源失控",
        "Fluent Bit（C 语言，5-30MB 内存）比 Fluentd（Ruby，100-300MB 内存）更适合 DaemonSet 场景；生产环境必须显式配置 kubelet 的 `--container-log-max-size` 和 `--container-log-max-files`，防止日志堆积耗尽节点磁盘触发 DiskPressure 驱逐"
      ],
      "quiz": [
        {
          "id": "monitoring-q61-quiz-1",
          "question": "Kubernetes 中，容器的 stdout/stderr 日志最终落盘到宿主机的哪个路径？",
          "choices": [
            { "id": "A", "text": "/var/log/pods/<namespace>_<pod-name>_<pod-uid>/<container-name>/0.log" },
            { "id": "B", "text": "/tmp/docker/containers/<container-id>/logs/output.log" },
            { "id": "C", "text": "/etc/kubernetes/logs/<namespace>/<pod-name>.log" },
            { "id": "D", "text": "/proc/<pid>/fd/1，直接挂载到进程的文件描述符" }
          ],
          "correctAnswer": "A",
          "explanation": "kubelet 通知容器运行时（containerd/CRI-O）将容器的 stdout/stderr 重定向并落盘到 `/var/log/pods/<namespace>_<pod-name>_<pod-uid>/<container-name>/0.log`，同时在 `/var/log/containers/` 下创建符号链接。这是 Kubernetes 日志路径的事实标准，DaemonSet 模式的日志 Agent 正是通过 hostPath 挂载这两个目录来读取所有容器日志的。选项 B 是 Docker 旧时代的路径约定（containerd 接管后已不再是主路径）；C 和 D 从未是 Kubernetes 的日志存储方式。"
        },
        {
          "id": "monitoring-q61-quiz-2",
          "question": "下列哪种应用场景最适合使用 Sidecar 模式收集日志，而非 DaemonSet 模式？",
          "choices": [
            { "id": "A", "text": "遗留 Java 服务通过 Logback 将日志写入容器内 /app/logs/ 目录，短期内无法改造为 stdout 输出" },
            { "id": "B", "text": "应用已将所有日志输出到 stdout/stderr，日志量约 500 行/秒" },
            { "id": "C", "text": "集群规模超过 500 个节点，需要降低整体运维复杂度" },
            { "id": "D", "text": "需要降低整体日志收集的 CPU 和内存消耗" }
          ],
          "correctAnswer": "A",
          "explanation": "DaemonSet Agent 通过宿主机 hostPath 挂载读取日志，只能访问容器的 stdout/stderr 落盘文件，无法看到容器 overlay filesystem 内部写入的应用日志文件。Sidecar 容器与业务容器共享 emptyDir Volume，因此可以直接读取业务容器写入文件的日志，这是 Sidecar 模式最核心的适用场景。选项 B 明显应该用 DaemonSet（stdout 输出正是 DaemonSet 的主场）；选项 C 集群越大 DaemonSet 的运维优势反而越明显（只需维护一份 DaemonSet 配置）；选项 D 恰好相反，Sidecar 的资源消耗远高于 DaemonSet。"
        },
        {
          "id": "monitoring-q61-quiz-3",
          "question": "相比 DaemonSet 模式，Sidecar 模式在哪个维度上具有明确优势？",
          "choices": [
            { "id": "A", "text": "可以收集容器文件系统内的日志文件，并具备 Pod 级别的日志处理隔离性" },
            { "id": "B", "text": "内存消耗更低，适合资源紧张的集群" },
            { "id": "C", "text": "升级维护更方便，只需更新一个 DaemonSet 配置即可全集群生效" },
            { "id": "D", "text": "不需要配置 RBAC 权限，开箱即用" }
          ],
          "correctAnswer": "A",
          "explanation": "Sidecar 模式的两个核心优势分别是：第一，可以读取容器内文件系统中的日志文件（DaemonSet 做不到）；第二，每个 Pod 有独立的 Sidecar 实例，天然实现 Pod 级别的日志处理隔离，每个 Sidecar 可以有不同的目的地配置，满足多租户场景的隔离要求。选项 B 恰好相反，Sidecar 的内存消耗远高于 DaemonSet；选项 C 描述的是 DaemonSet 的优势，而非 Sidecar；选项 D 也是错的，Sidecar 同样需要配置对应的 RBAC 或 ServiceAccount。"
        },
        {
          "id": "monitoring-q61-quiz-4",
          "question": "200 节点、每节点平均 20 个 Pod 的集群，若全部改为 Sidecar 模式（每 Sidecar 申请 64Mi 内存），总日志收集内存消耗约为多少？",
          "choices": [
            { "id": "A", "text": "约 256GB" },
            { "id": "B", "text": "约 12.8GB" },
            { "id": "C", "text": "约 6.4GB" },
            { "id": "D", "text": "约 25.6GB" }
          ],
          "correctAnswer": "A",
          "explanation": "计算过程：200 节点 × 20 Pod/节点 = 4000 个 Pod，每个 Pod 注入一个 Sidecar，共 4000 个 Sidecar 实例。每实例申请 64Mi = 0.0625GB，总计 4000 × 0.0625GB = 250GB，约 256GB（按 2 的幂次四舍五入）。相比之下，同等集群的 DaemonSet 方案只需 200 个 Fluent Bit 实例，每实例 ~30MB，总计约 6GB，相差约 40 倍。选项 B（12.8GB）是误算成 200 个实例的结果；选项 C（6.4GB）是 DaemonSet 模式的大约消耗；选项 D（25.6GB）可能是误用了每实例 32Mi 计算。"
        },
        {
          "id": "monitoring-q61-quiz-5",
          "question": "以下关于 /var/log/containers/ 目录内容的描述，正确的是？",
          "choices": [
            { "id": "A", "text": "该目录下是指向 /var/log/pods/ 实际日志文件的符号链接，文件名包含 pod 名、namespace 和 container-id 信息" },
            { "id": "B", "text": "该目录直接存储容器日志文件的内容，DaemonSet Agent 在此读写日志" },
            { "id": "C", "text": "该目录由 Kubernetes API Server 管理，通过 etcd 持久化日志元数据" },
            { "id": "D", "text": "该目录仅在 Docker 运行时下存在，使用 containerd 时日志路径不同" }
          ],
          "correctAnswer": "A",
          "explanation": "/var/log/containers/ 目录下存放的是符号链接（symlink），每个链接格式为 `<pod-name>_<namespace>_<container-name>-<container-id>.log`，实际指向 `/var/log/pods/<namespace>_<pod-name>_<pod-uid>/<container-name>/0.log`。Fluent Bit、Filebeat 等 Agent 通过这些符号链接读取日志，同时可以从文件名中解析出 namespace、pod 名等元数据附加到日志条目中。该目录是 Kubernetes 的标准约定，无论使用 containerd 还是 CRI-O 都遵循这个约定；日志内容不经过 API Server 或 etcd。"
        },
        {
          "id": "monitoring-q61-quiz-6",
          "question": "以下哪项是 DaemonSet 模式的根本性局限，而非配置或优化问题？",
          "choices": [
            { "id": "A", "text": "只能收集 stdout/stderr 日志，无法访问容器 overlay filesystem 内的日志文件" },
            { "id": "B", "text": "DaemonSet Agent 无法在 kube-system 命名空间中运行" },
            { "id": "C", "text": "DaemonSet 模式不支持 Fluent Bit，只能使用 Fluentd" },
            { "id": "D", "text": "DaemonSet Agent 无法将 Pod 的 label 和 annotation 附加到日志条目中" }
          ],
          "correctAnswer": "A",
          "explanation": "这是 DaemonSet 模式的架构性限制，无法通过配置绕过：DaemonSet Agent 通过宿主机 hostPath 挂载读取日志，只能看到 kubelet 写到 `/var/log/pods/` 的 stdout/stderr 文件，容器内 overlay filesystem 层（容器自己写入的文件）对宿主机进程是不可见的。这正是 Sidecar 模式存在的核心原因。选项 B 是错误的，kube-system 是日志 Agent DaemonSet 最常见的部署命名空间；选项 C 完全错误，Fluent Bit 是 DaemonSet 场景最主流的选择；选项 D 也是错的，现代 Agent 可以通过 Kubernetes API 或读取日志文件名来丰富元数据。"
        },
        {
          "id": "monitoring-q61-quiz-7",
          "question": "在多租户 Kubernetes 集群中，为什么 Sidecar 模式比 DaemonSet 更适合有强隔离要求的场景？",
          "choices": [
            { "id": "A", "text": "DaemonSet 的单 Agent 进程读取节点上所有 Pod 的日志，存在跨租户数据被同一进程访问的安全风险" },
            { "id": "B", "text": "Sidecar 的日志采集延迟比 DaemonSet 低，更适合实时性要求高的场景" },
            { "id": "C", "text": "DaemonSet 不支持 mTLS 加密传输，而 Sidecar 可以为每个 Pod 配置独立证书" },
            { "id": "D", "text": "Sidecar 模式下日志数据不经过宿主机文件系统，安全性更高" }
          ],
          "correctAnswer": "A",
          "explanation": "DaemonSet 模式下，一个 Agent 进程会读取该节点上所有 Pod 的日志，包括不同租户的工作负载。如果 Agent 存在安全漏洞，或者某个租户能够影响 Agent 的行为（例如通过注入特殊格式日志触发解析漏洞），就可能导致跨租户的数据泄露。Sidecar 模式每个 Pod 独立运行一个 Agent 进程，进程之间完全隔离，符合「最小权限原则」。选项 B 描述的延迟优势并不符合实际（DaemonSet 延迟通常更低，因为直接读本地文件）；选项 C 和 D 描述的特性与隔离需求无关，且 DaemonSet 同样支持 TLS 配置。"
        },
        {
          "id": "monitoring-q61-quiz-8",
          "question": "DaemonSet 日志 Agent 落后于日志产生速度（如下游 Elasticsearch 抖动）时，最可能引发的集群级故障是？",
          "choices": [
            { "id": "A", "text": "/var/log/pods 目录堆积导致节点磁盘耗尽，触发 kubelet DiskPressure 驱逐健康 Pod" },
            { "id": "B", "text": "Kubernetes API Server 被大量日志写入请求打爆，导致集群控制面不可用" },
            { "id": "C", "text": "Pod 因日志写入失败（stdout 写满）而自动重启，出现 CrashLoopBackOff" },
            { "id": "D", "text": "kubelet 会自动暂停产生日志过多的容器，等待 Agent 追上进度" }
          ],
          "correctAnswer": "A",
          "explanation": "当日志 Agent 无法及时转发日志时，kubelet 写到 `/var/log/pods/` 的日志文件会持续增长，占用宿主机磁盘空间。虽然 kubelet 有 `--container-log-max-size` 和 `--container-log-max-files` 参数控制单容器日志文件的 rotation（默认 10Mi × 5 = 50Mi/容器），但如果参数设置不当或节点上 Pod 数量很多，仍可能导致磁盘耗尽。一旦触发 `DiskPressure` 条件，kubelet 会开始驱逐 Pod（即使这些 Pod 完全健康），造成非预期的服务中断。选项 B、C、D 描述的现象在 Kubernetes 中不会发生：日志直接写入文件系统而不经过 API Server；stdout 是 pipe，写慢会阻塞应用但不会导致 CrashLoopBackOff；kubelet 也不会主动暂停容器。",
          "relatedConcepts": ["DiskPressure", "kubelet eviction", "log rotation"]
        },
        {
          "id": "monitoring-q61-quiz-9",
          "question": "Kubernetes 1.29 引入 Sidecar Container GA 特性后，如何通过配置实现 Sidecar 独立于主容器的生命周期？",
          "choices": [
            { "id": "A", "text": "在 initContainers 中定义 Sidecar 容器并配置 restartPolicy: Always" },
            { "id": "B", "text": "在 Pod spec 中使用新增的独立 sidecars 字段定义 Sidecar 容器列表" },
            { "id": "C", "text": "通过 Pod 的 lifecycle.postStart 钩子在主容器启动后注入 Sidecar 进程" },
            { "id": "D", "text": "为 Sidecar 容器设置 terminationMessagePolicy: FallbackToLogsOnError 触发独立重启逻辑" }
          ],
          "correctAnswer": "A",
          "explanation": "Kubernetes 1.29 的 Sidecar Container 特性并没有引入新的 `sidecars` 字段，而是复用了现有的 `initContainers`，但允许为其中的容器配置 `restartPolicy: Always`。这样的容器会在 Pod 生命周期内持续运行，不像普通 initContainer 那样「运行完即退出」，也不像普通容器那样与 Pod 的主容器生命周期完全绑定。这个设计使得 Sidecar 可以在主容器退出后继续运行一段时间（排空日志缓冲），再优雅退出，解决了长期以来日志丢失的问题。选项 B 描述的 `sidecars` 字段从未被采纳到正式规范；选项 C 和 D 描述的机制与 Sidecar 生命周期管理无关。"
        },
        {
          "id": "monitoring-q61-quiz-10",
          "question": "在大规模 Kubernetes 集群（200+ 节点）中，为什么通常选择 Fluent Bit 而非 Fluentd 作为 DaemonSet 日志 Agent？",
          "choices": [
            { "id": "A", "text": "Fluent Bit 是 C 语言实现，内存占用通常只有 5-30MB，而同等吞吐下 Fluentd（Ruby）需要 100-300MB，节省成本显著" },
            { "id": "B", "text": "Fluentd 不支持解析 Kubernetes 标准日志格式（JSON + 元数据），而 Fluent Bit 原生支持" },
            { "id": "C", "text": "Fluentd 无法以 DaemonSet 形式部署，只能作为独立进程运行在节点上" },
            { "id": "D", "text": "Fluentd 不支持将日志发送到 Elasticsearch，Fluent Bit 有更丰富的输出插件" }
          ],
          "correctAnswer": "A",
          "explanation": "Fluent Bit 和 Fluentd 都由 CNCF 旗下的 Fluent 项目维护，都支持 Kubernetes 元数据解析、多种输出目的地（Elasticsearch、Kafka、Loki 等），且都可以部署为 DaemonSet。两者最关键的差异是资源消耗：Fluent Bit 用 C 语言编写，设计目标就是嵌入式和边缘场景，内存通常在 5-30MB；Fluentd 用 Ruby 编写，有更丰富的插件生态，但同等吞吐下内存消耗达 100-300MB。在 200 节点集群中，Fluent Bit 总内存约 200 × 30MB = 6GB，Fluentd 则可能达 200 × 200MB = 40GB，差距明显。选项 B、C、D 的描述均不符合实际，Fluentd 同样支持 Kubernetes 日志解析、DaemonSet 部署方式和 Elasticsearch 输出。"
        }
      ],
      "references": [
        "https://kubernetes.io/docs/concepts/cluster-administration/logging/",
        "https://docs.fluentbit.io/manual/installation/kubernetes",
        "https://kubernetes.io/blog/2023/08/25/native-sidecar-containers/",
        "https://12factor.net/logs"
      ]
    }
  ]
}
