{
  "id": "k8s-keda-vs-native-hpa",
  "name": "KEDA 与原生 HPA 的对比",
  "domain": "kubernetes",
  "description": "深度对比 KEDA 事件驱动自动伸缩与 Kubernetes 原生 HPA 在触发源、缩零能力、架构设计与生产选型上的差异",
  "version": "1.0.0",
  "questions": [
    {
      "id": "k8s-keda-vs-native-hpa-q1",
      "domain": "kubernetes",
      "type": "comparison",
      "difficulty": 3,
      "tags": ["KEDA", "HPA", "Horizontal Pod Autoscaler", "事件驱动", "自动伸缩", "ScaledObject", "ScaledJob", "Autoscaling", "Kafka", "RabbitMQ"],
      "title": "KEDA（Kubernetes Event-Driven Autoscaler）与原生 HPA 有什么区别？",
      "content": "## 面试场景\n\n你所在的团队负责一个运行在 Kubernetes 1.30 集群上的电商订单处理平台。平台的核心链路是：用户下单后，订单事件被发送到 Kafka Topic `order-events`（3 个 Partition），下游有一组 Consumer Pod（Deployment `order-processor`，当前固定 3 副本）负责消费并处理订单——包括库存扣减、优惠计算和写入数据库。另外还有一组 RabbitMQ 消费者（Deployment `notification-sender`，固定 2 副本）负责从队列 `email-notifications` 中拉取消息发送通知邮件。\n\n现在遇到了两个问题。第一，大促期间 Kafka Topic 的消息积压（Consumer Lag）从平时的几百条飙升到 50 万条，3 个 Consumer Pod 根本处理不过来，但因为 CPU 利用率只有 40% 左右——消费者大部分时间在等 I/O 和数据库写入——所以基于 CPU 的 HPA 完全不触发扩容。运维同事试过用 `kubectl autoscale` 把目标 CPU 利用率降到 20%，结果平时也维持了多余的 Pod，浪费严重。第二，凌晨 0 点到早上 7 点几乎没有邮件通知需求，但 `notification-sender` 的 2 个 Pod 一直空转，每月白白消耗了约 $180 的计算资源。运维想把 `minReplicas` 设为 0，但发现原生 HPA 的 `minReplicas` 最低只能设为 1。\n\n架构师在周会上提到了 KEDA（Kubernetes Event-Driven Autoscaler），说它可以根据 Kafka Consumer Lag 自动扩缩 Pod，还能缩到 0 副本。你之前只用过原生 HPA，对 KEDA 不太了解。CTO 让你做一个技术调研，回答以下问题：\n\n### 问题\n\n请解释 KEDA 的核心架构和工作原理，对比 KEDA 与原生 HPA 在触发源类型、缩零能力、指标驱动模型等维度的差异，并给出电商平台上述两个场景的 KEDA 配置方案和生产选型建议。",
      "answer": "## 第一步：Kubernetes 自动伸缩体系与 HPA 基础\n\n要理解 KEDA 的价值，必须先搞清楚 Kubernetes 原生 HPA（Horizontal Pod Autoscaler）能做什么、不能做什么。HPA 是 Kubernetes 内置的水平自动伸缩控制器，从 1.1 版本就开始支持，到 1.23 正式 GA 了 `autoscaling/v2` API。它的核心工作原理很直白：每隔 15 秒（默认值，由 `--horizontal-pod-autoscaler-sync-period` 控制）从 Metrics API 拉取指标数据，然后用公式 `desiredReplicas = ceil[currentReplicas × (currentMetricValue / desiredMetricValue)]` 计算期望副本数，最后通过 Scale 子资源调整 Deployment 或 StatefulSet 的 replicas 字段。\n\n一个最基础的 HPA 配置长这样：\n\n```yaml\napiVersion: autoscaling/v2\nkind: HorizontalPodAutoscaler\nmetadata:\n  name: order-processor-hpa\nspec:\n  scaleTargetRef:\n    apiVersion: apps/v1\n    kind: Deployment\n    name: order-processor\n  minReplicas: 1        # 注意：最小值只能是 1，不能是 0\n  maxReplicas: 20\n  metrics:\n  - type: Resource\n    resource:\n      name: cpu\n      target:\n        type: Utilization\n        averageUtilization: 60\n```\n\nHPA 支持四种指标类型：Resource（CPU/内存利用率）、Pods（每个 Pod 的自定义指标均值）、Object（集群内 Kubernetes 对象的指标）和 External（集群外部系统的指标）。理论上通过 External 类型你可以对接任何外部指标源，但这条路并不好走——你需要自己部署一个实现了 `external.metrics.k8s.io` API 的 Custom Metrics Adapter（比如 Prometheus Adapter），编写复杂的 PromQL 规则把 Kafka Consumer Lag 映射为 Kubernetes External Metrics API 的格式，然后在 HPA 里引用。更致命的是，HPA 的 `minReplicas` 字段有一个硬限制：最小值为 1，不能设为 0。也就是说，即使没有任何负载，HPA 管理的 Deployment 至少保留一个 Pod 在运行。这对事件驱动型的消费者服务来说，是一个无法绕过的资源浪费。\n\n## 第二步：KEDA 核心架构与工作原理\n\nKEDA 全称 Kubernetes Event-Driven Autoscaler，由微软和红帽在 2019 年联合发起，2021 年成为 CNCF Incubating 项目，2024 年 8 月正式毕业为 CNCF Graduated 项目——这意味着它已经通过了安全审计和成熟度评估，跟 Kubernetes、Prometheus、Envoy 同一级别。截至 KEDA 2.16（2024 年 12 月发布），它支持 70+ 种内置 Scaler，覆盖了 Kafka、RabbitMQ、AWS SQS、Azure Service Bus、Redis Streams、PostgreSQL、MySQL、Prometheus、Elasticsearch、GCP Pub/Sub 等几乎所有主流事件源和数据存储。\n\nKEDA 的核心架构由三个组件构成。第一个是 **KEDA Operator**（也叫 Controller），它是一个运行在集群中的 Deployment（通常部署在 `keda` namespace），负责 watch 两种 CRD 资源——ScaledObject 和 ScaledJob——并根据它们的定义创建和管理底层的 HPA 对象。关键点在于 KEDA 并不是替代 HPA，而是在 HPA 之上加了一层。当副本数大于 0 时，KEDA 实际上是生成一个 HPA 来管理扩缩；当需要缩到 0 或从 0 扩到 1 时，KEDA Operator 自己直接操作 Deployment 的 replicas 字段，因为 HPA 不支持 0 副本。\n\n第二个组件是 **KEDA Metrics Server**，它实现了 Kubernetes 的 `external.metrics.k8s.io` API，替代了你手动部署 Prometheus Adapter 的工作。KEDA Metrics Server 从各个 Scaler 拉取指标数据，然后以标准的 External Metrics API 格式暴露给 HPA 消费。这样一来，HPA 依然是真正执行扩缩决策的控制器，KEDA 只是一个更智能的「指标翻译层」加「零副本管理器」。\n\n第三个组件是 **KEDA Admission Webhooks**（从 2.10 开始引入），用于在创建 ScaledObject/ScaledJob 时校验配置合法性，避免出现同一个 Deployment 被多个 ScaledObject 管理的冲突。\n\n用一个 ScaledObject 配置来说明 KEDA 的用法，以题目中的 Kafka 消费者场景为例：\n\n```yaml\napiVersion: keda.sh/v1alpha1\nkind: ScaledObject\nmetadata:\n  name: order-processor-scaledobject\n  namespace: production\nspec:\n  scaleTargetRef:\n    name: order-processor           # 目标 Deployment\n  pollingInterval: 15               # 每 15 秒查询一次指标\n  cooldownPeriod: 300               # 缩到 0 前等待 300 秒\n  idleReplicaCount: 0               # 无事件时缩到 0 副本\n  minReplicaCount: 1                # 活跃时最少 1 副本\n  maxReplicaCount: 30               # 最多 30 副本\n  triggers:\n  - type: kafka\n    metadata:\n      bootstrapServers: kafka-cluster:9092\n      consumerGroup: order-processor-group\n      topic: order-events\n      lagThreshold: \"100\"           # 每个 Partition 积压超过 100 条就触发扩容\n      activationLagThreshold: \"5\"   # Lag > 5 时从 0 唤醒到 minReplicaCount\n      offsetResetPolicy: latest\n```\n\n这段配置背后的工作流程是这样的：KEDA Operator watch 到这个 ScaledObject 后，首先检查 Kafka 的 Consumer Lag。如果所有 Partition 的 Lag 总和为 0 或低于 `activationLagThreshold`（5 条），KEDA 直接把 `order-processor` 的 replicas 设为 0——这个动作是 KEDA Operator 自己做的，不经过 HPA。一旦某个 Partition 的 Lag 超过了 5 条，KEDA 立即把 replicas 从 0 拉到 `minReplicaCount`（1），同时创建一个 HPA 对象来接管后续的扩缩。HPA 通过 KEDA Metrics Server 获取 Kafka Lag 指标，用标准算法计算期望副本数——比如 3 个 Partition 总 Lag 15000 条，`lagThreshold` 是 100，那期望副本数 = ceil(15000 / 100) = 150，但 `maxReplicaCount` 限制为 30，最终扩到 30。当 Lag 消化完毕，HPA 逐步缩容到 `minReplicaCount`（1），然后 KEDA Operator 等待 `cooldownPeriod`（300 秒），如果持续没有新消息，再把副本数从 1 缩到 0。\n\n## 第三步：KEDA vs 原生 HPA 多维度深度对比\n\n### 触发源与指标驱动模型\n\n原生 HPA 的设计哲学是「指标驱动」——它从 Metrics API 拉取数值型指标，然后做数学计算。这套模型对 CPU/内存这类线性指标非常有效，但对事件驱动型工作负载来说存在根本性的语义失配。Kafka 消费者的性能瓶颈往往不在 CPU 而在 I/O 等待和下游处理延迟，CPU 利用率 40% 但 Lag 已经积压几十万条是常见的情况。你可以通过 Prometheus Adapter 把 Lag 暴露为 External Metrics，但这需要你自己维护一套 PromQL → Metrics API 的映射规则，每加一个 Topic 就要改一次配置。\n\nKEDA 的设计哲学是「事件驱动」——它内置了 70+ 种 Scaler，每种 Scaler 直接跟对应的事件源通信（Kafka Scaler 通过 Kafka Admin Client 查 Consumer Group 的 Lag，RabbitMQ Scaler 通过 Management API 查队列深度，AWS SQS Scaler 通过 AWS SDK 查 `ApproximateNumberOfMessages`）。你不需要先把指标收集到 Prometheus 再做转换，KEDA 直接拿到原始的业务指标。而且 KEDA 支持在一个 ScaledObject 中配置多个 trigger——比如同时基于 Kafka Lag 和 Prometheus 查询的 P99 延迟来做扩缩决策，取两者中要求副本数更多的那个值。\n\n### 缩零能力（Scale-to-Zero）\n\n这是 KEDA 最核心也是最有区分度的能力。原生 HPA 的 `minReplicas` 最低为 1，这是 Kubernetes API 的硬约束——`autoscaling/v2` 的 OpenAPI Schema 中明确定义了 `minReplicas` 的 minimum 为 1。而 KEDA 通过 `idleReplicaCount: 0` 实现了真正的缩到零副本。实现方式是 KEDA Operator 直接 patch Deployment 的 replicas 为 0，绕过了 HPA。当从 0 唤醒时，KEDA 也是直接 patch replicas 到 `minReplicaCount`，然后再创建 HPA 接管后续扩缩。\n\n缩零在实际生产中的价值取决于你的工作负载模式。对 7×24 运行的核心服务，缩到 0 毫无意义（而且冷启动延迟不可接受）。但对于题目中的 `notification-sender` 这种凌晨完全无流量的批处理/消费型服务，每天 7 小时的缩零可以节省约 30% 的计算成本。用 RabbitMQ 场景的 ScaledObject 来说明：\n\n```yaml\napiVersion: keda.sh/v1alpha1\nkind: ScaledObject\nmetadata:\n  name: notification-sender-scaledobject\nspec:\n  scaleTargetRef:\n    name: notification-sender\n  pollingInterval: 30\n  cooldownPeriod: 600               # 10 分钟无消息才缩到 0\n  idleReplicaCount: 0\n  minReplicaCount: 1\n  maxReplicaCount: 10\n  triggers:\n  - type: rabbitmq\n    metadata:\n      protocol: auto\n      queueName: email-notifications\n      mode: QueueLength\n      value: \"50\"                   # 每 50 条消息增加一个副本\n      activationValue: \"1\"          # 队列中出现 1 条消息就唤醒\n      host: amqp://guest:guest@rabbitmq.production:5672/\n```\n\n### ScaledObject 与 ScaledJob 的区别\n\nKEDA 提供了两种 CRD。ScaledObject 用于管理长期运行的 Deployment/StatefulSet，适合持续消费型工作负载，比如 Kafka 消费者。ScaledJob 用于管理 Kubernetes Job，适合「来一批事件创建一批一次性任务」的场景——比如每收到一个视频上传事件就创建一个转码 Job。ScaledJob 的 `maxReplicaCount` 控制的是并发 Job 的上限，Job 完成后自动清理，天然具备缩零能力。\n\n以下汇总两者核心差异：\n\n| 维度 | 原生 HPA | KEDA |\n|------|----------|------|\n| 最低副本数 | minReplicas ≥ 1 | idleReplicaCount 可设为 0 |\n| 内置触发源 | CPU、内存、自定义指标（需 Adapter） | 70+ 内置 Scaler，开箱即用 |\n| 外部指标对接 | 需手动部署 Prometheus Adapter + PromQL | Scaler 直连事件源，零额外配置 |\n| 管理对象 | Deployment / StatefulSet / ReplicaSet | Deployment / StatefulSet / Job / 自定义资源 |\n| 多指标联合 | 支持，取最大值 | 支持多 trigger，取最大值 |\n| 冷启动控制 | 无（至少 1 个 Pod） | cooldownPeriod + activationValue 精细控制 |\n| 与 HPA 关系 | 原生组件 | 上层封装，底层仍创建 HPA |\n\n## 第四步：生产部署与选型建议\n\n### KEDA 部署方式\n\n在生产环境中，推荐通过 Helm 安装 KEDA 2.16：\n\n```bash\n$ helm repo add kedacore https://kedacore.github.io/charts\n$ helm repo update\n$ helm install keda kedacore/keda \\\n    --namespace keda \\\n    --create-namespace \\\n    --version 2.16.1 \\\n    --set resources.operator.requests.cpu=100m \\\n    --set resources.operator.requests.memory=128Mi \\\n    --set resources.metricServer.requests.cpu=100m \\\n    --set resources.metricServer.requests.memory=128Mi\n\n$ kubectl get pods -n keda\nNAME                                      READY   STATUS    RESTARTS   AGE\nkeda-admission-webhooks-6f4d7bc95-x2vml   1/1     Running   0          32s\nkeda-operator-7b9d4b5f6c-8kqzn            1/1     Running   0          32s\nkeda-operator-metrics-apiserver-5d8c-rk7   1/1     Running   0          32s\n```\n\n安装完成后集群中会多出三个 Deployment（Operator、Metrics Server、Admission Webhooks）和两个 CRD（ScaledObject、ScaledJob）。KEDA 本身的资源开销很小——默认情况下 Operator 的 CPU 使用量在 10-50m 之间，内存在 50-100Mi，即使管理上百个 ScaledObject 也不会成为瓶颈。\n\n### 常见坑点\n\n第一个坑是 KEDA 和原生 HPA 的冲突。如果你的 Deployment 已经有一个手动创建的 HPA，又给它创建了 ScaledObject，KEDA 会尝试创建另一个 HPA，导致两个 HPA 同时管理一个 Deployment，副本数会不断震荡。正确做法是让 KEDA 全权管理，删除手动创建的 HPA。你可以通过 `kubectl get hpa` 看到 KEDA 自动创建的 HPA 对象名称格式是 `keda-hpa-{scaledobject-name}`。\n\n第二个坑是 Kafka Scaler 的认证配置。生产环境的 Kafka 集群通常开启了 SASL/SSL，你需要通过 TriggerAuthentication CRD 把凭据传给 KEDA：\n\n```yaml\napiVersion: keda.sh/v1alpha1\nkind: TriggerAuthentication\nmetadata:\n  name: kafka-auth\nspec:\n  secretTargetRef:\n  - parameter: sasl\n    name: kafka-secrets\n    key: sasl\n  - parameter: tls\n    name: kafka-secrets\n    key: tls\n  - parameter: username\n    name: kafka-secrets\n    key: username\n  - parameter: password\n    name: kafka-secrets\n    key: password\n```\n\n然后在 ScaledObject 的 trigger 中通过 `authenticationRef` 引用这个 TriggerAuthentication。\n\n第三个坑是冷启动延迟。缩到 0 意味着第一条消息到达时需要等 Pod 从无到有启动完成才能开始处理。如果你的镜像比较大（超过 500MB）或者服务启动慢（比如 Java 应用需要 30 秒以上），这个冷启动延迟可能导致消息处理的 SLA 不达标。解决思路包括：使用小镜像（Go/Rust 编译的二进制通常 10-20MB）、预拉取镜像到节点（DaemonSet + initContainer 的模式）、或者把 `idleReplicaCount` 设为 1 而不是 0——保留一个最小副本来处理零星请求，通过 `minReplicaCount` 控制活跃期的下限。\n\n### 生产选型决策树\n\n什么时候该用原生 HPA？如果你的工作负载是典型的 Web API 服务，性能瓶颈主要在 CPU（比如计算密集型的 API），请求量和 CPU 利用率呈正相关，而且服务需要 7×24 运行不能缩零——那原生 HPA 完全够用，不需要引入额外的组件。原生 HPA 的优势是零依赖、零额外运维成本，而且经过了十多年的生产验证。\n\n什么时候该用 KEDA？当你遇到以下任意一种场景时：工作负载是事件/消息驱动的消费者，CPU 利用率与负载压力不相关（I/O 密集型）；需要缩到零副本来节省成本（批处理、定时任务、低流量时段的消费者）；需要基于 Kafka Lag、队列深度、Cron 表达式等非标准指标做扩缩，但不想维护 Prometheus Adapter 的复杂配置。KEDA 作为 CNCF Graduated 项目，生产稳定性已经得到了充分验证——阿里云 ASK、Azure AKS、AWS EKS 都在官方文档中推荐使用 KEDA 作为事件驱动自动伸缩方案。\n\n还有一种混合模式值得考虑：在同一个集群中，Web API 类 Deployment 用原生 HPA 基于 CPU 扩缩，消息消费者类 Deployment 用 KEDA 基于队列深度扩缩。两者完全可以共存，KEDA 的 Metrics Server 不会干扰原生 Metrics Server 的运行——它们注册在不同的 API Group 下（KEDA 注册 `external.metrics.k8s.io`，原生 Metrics Server 注册 `metrics.k8s.io`）。",
      "keyPoints": [
        "KEDA 是 CNCF Graduated 项目（2024 年毕业），在 HPA 之上增加了事件驱动伸缩层，底层仍通过创建 HPA 对象实现 1→N 的扩缩，但自己管理 0↔1 的切换",
        "原生 HPA 的 minReplicas 最低为 1（API 硬约束），KEDA 通过 idleReplicaCount: 0 直接 patch Deployment replicas 实现真正的缩零",
        "KEDA 2.16 内置 70+ 种 Scaler，直连 Kafka/RabbitMQ/SQS/Prometheus 等事件源获取指标，省去了手动部署和维护 Prometheus Adapter 的成本",
        "ScaledObject 管理长运行 Deployment/StatefulSet 适合持续消费型负载，ScaledJob 管理 Kubernetes Job 适合一次性事件处理任务",
        "KEDA 和手动创建的 HPA 不能同时管理同一个 Deployment，否则两个 HPA 会争抢 replicas 字段导致副本数震荡",
        "缩零场景的冷启动延迟是关键考量——镜像大小、服务启动时间、消息处理 SLA 共同决定是否适合缩到 0 还是保留 1 个最小副本",
        "生产选型原则：CPU 相关的 Web API 用原生 HPA，I/O 密集的消息消费者用 KEDA，两者在同一集群中可以共存互不干扰",
        "TriggerAuthentication CRD 用于安全地向 KEDA Scaler 传递 Kafka SASL/SSL、RabbitMQ 连接字符串等敏感凭据"
      ],
      "quiz": [
        {
          "id": "k8s-keda-vs-native-hpa-q1-quiz1",
          "question": "KEDA 在 CNCF 中的项目级别是什么？",
          "choices": [
            {"id": "A", "text": "Sandbox（沙箱）级别，尚处于早期实验阶段"},
            {"id": "B", "text": "Incubating（孵化）级别，正在逐步成熟"},
            {"id": "C", "text": "Graduated（毕业）级别，已通过安全审计和成熟度评估"},
            {"id": "D", "text": "KEDA 不属于 CNCF，它是微软的商业产品"}
          ],
          "correctAnswer": "C",
          "explanation": "KEDA 于 2021 年进入 CNCF Incubating 阶段，2024 年 8 月正式毕业成为 CNCF Graduated 项目，与 Kubernetes、Prometheus、Envoy 处于同一级别。Graduated 意味着项目已经通过了独立的安全审计、具备成熟的治理结构和广泛的生产采用。A 和 B 都是 KEDA 曾经经历的阶段但已经过去了。D 完全错误，KEDA 虽然由微软和红帽联合发起，但一直是开源项目并捐赠给了 CNCF。"
        },
        {
          "id": "k8s-keda-vs-native-hpa-q1-quiz2",
          "question": "KEDA 实现缩到 0 副本的底层机制是什么？",
          "choices": [
            {"id": "A", "text": "KEDA 修改 HPA 的 minReplicas 为 0，让 HPA 自己管理缩零"},
            {"id": "B", "text": "KEDA Operator 直接 patch Deployment 的 replicas 为 0，绕过 HPA，因为 HPA 的 minReplicas 最低只能是 1"},
            {"id": "C", "text": "KEDA 删除 Deployment 对象并在需要时重新创建"},
            {"id": "D", "text": "KEDA 通过向 kubelet 发送信号来暂停所有 Pod 的容器进程"}
          ],
          "correctAnswer": "B",
          "explanation": "HPA 的 autoscaling/v2 API 明确限定了 minReplicas 的最小值为 1，这是 Kubernetes API 的硬约束，不是 KEDA 能修改的。所以 KEDA 的做法是：当指标低于 activationValue 且超过 cooldownPeriod 后，KEDA Operator 直接 patch Deployment 的 spec.replicas 为 0，同时删除它之前创建的 HPA 对象。唤醒时反过来——先 patch replicas 到 minReplicaCount，再创建新的 HPA。A 不可能因为 API 不允许。C 删除重建 Deployment 会丢失所有配置和历史记录。D 是完全编造的机制。"
        },
        {
          "id": "k8s-keda-vs-native-hpa-q1-quiz3",
          "question": "在 KEDA 的 ScaledObject 中，activationLagThreshold 和 lagThreshold 分别控制什么行为？",
          "choices": [
            {"id": "A", "text": "activationLagThreshold 控制从 0 唤醒到 minReplicaCount 的阈值，lagThreshold 控制 1→N 扩缩时每个副本承担的 Lag 量"},
            {"id": "B", "text": "两者功能相同，activationLagThreshold 是 lagThreshold 的别名"},
            {"id": "C", "text": "activationLagThreshold 控制缩容速度，lagThreshold 控制扩容速度"},
            {"id": "D", "text": "activationLagThreshold 是 Kafka Broker 端的参数，lagThreshold 是 KEDA 端的参数"}
          ],
          "correctAnswer": "A",
          "explanation": "KEDA 的 Kafka Scaler 有两个阈值分别控制两个阶段。activationLagThreshold（默认值 0）是「从 0 到 1」的唤醒阈值——当 Consumer Lag 超过这个值时，KEDA Operator 把副本数从 idleReplicaCount（0）拉到 minReplicaCount。lagThreshold（默认值 10）是「从 1 到 N」阶段 HPA 使用的目标值——HPA 用 totalLag / lagThreshold 来计算期望副本数。B 错误，两者控制的是完全不同的伸缩阶段。C 颠倒了语义。D 混淆了 Kafka 配置和 KEDA 配置的边界。"
        },
        {
          "id": "k8s-keda-vs-native-hpa-q1-quiz4",
          "question": "KEDA 的三个核心组件——Operator、Metrics Server、Admission Webhooks——分别承担什么职责？",
          "choices": [
            {"id": "A", "text": "Operator watch ScaledObject 并管理 0↔1 切换及 HPA 生命周期；Metrics Server 实现 external.metrics.k8s.io API 供 HPA 消费；Admission Webhooks 校验 CRD 配置合法性"},
            {"id": "B", "text": "Operator 负责拉取所有指标数据；Metrics Server 做扩缩决策；Admission Webhooks 注入 sidecar 容器"},
            {"id": "C", "text": "三个组件功能完全相同，只是做了高可用副本"},
            {"id": "D", "text": "Operator 只负责安装 CRD；Metrics Server 负责所有扩缩逻辑；Admission Webhooks 是可选的日志组件"}
          ],
          "correctAnswer": "A",
          "explanation": "KEDA 的架构分工非常清晰。Operator（Controller）是核心大脑，它 watch ScaledObject/ScaledJob CRD，负责两件事：一是管理 0↔1 的切换（直接 patch Deployment replicas），二是管理 HPA 的创建和删除生命周期。Metrics Server 实现了 Kubernetes 的 external.metrics.k8s.io API，从各个 Scaler（Kafka、RabbitMQ 等）拉取指标数据，翻译成 HPA 能消费的标准格式。Admission Webhooks 是一个 Validating/Mutating Webhook，在创建 ScaledObject 时校验配置（比如同一 Deployment 不能被两个 ScaledObject 管理）。B 混淆了 Operator 和 Metrics Server 的职责，且 Webhooks 不注入 sidecar。"
        },
        {
          "id": "k8s-keda-vs-native-hpa-q1-quiz5",
          "question": "你执行 kubectl get hpa 看到如下输出，这个 HPA 是谁创建的？它的 TARGETS 值代表什么？\n\n```\nNAME                                    REFERENCE                    TARGETS        MINPODS   MAXPODS   REPLICAS\nkeda-hpa-order-processor-scaledobject   Deployment/order-processor   15000/100 (avg)   1         30        15\n```",
          "choices": [
            {"id": "A", "text": "这是手动创建的 HPA，15000/100 代表 CPU 利用率 15000%"},
            {"id": "B", "text": "这是 KEDA Operator 自动创建的 HPA，15000 是 Kafka Consumer Lag 总量，100 是 lagThreshold 目标值，当前 15 副本"},
            {"id": "C", "text": "这是 VPA 创建的 HPA，15000 是推荐的内存 requests"},
            {"id": "D", "text": "这是 Cluster Autoscaler 创建的 HPA，15000 是节点数量"}
          ],
          "correctAnswer": "B",
          "explanation": "KEDA 自动创建的 HPA 对象名称格式是 `keda-hpa-{scaledobject-name}`，所以 `keda-hpa-order-processor-scaledobject` 明确表示这是 KEDA 为名为 `order-processor-scaledobject` 的 ScaledObject 创建的 HPA。TARGETS 列的 `15000/100 (avg)` 表示当前 Kafka Consumer Lag 的指标值是 15000，目标值是 100（即 lagThreshold），HPA 用 ceil(15000/100)=150 计算期望副本数，但受 maxReplicas=30 限制，当前维持 15 个副本说明正在追赶积压。A 错在名称前缀 keda-hpa 说明不是手动创建的，且 CPU 不会是 15000%。C 和 D 都是完全无关的组件。"
        },
        {
          "id": "k8s-keda-vs-native-hpa-q1-quiz6",
          "question": "一个 Deployment 已经有一个手动创建的 HPA（基于 CPU），现在又给它创建了一个 KEDA ScaledObject（基于 Kafka Lag）。会发生什么？",
          "choices": [
            {"id": "A", "text": "KEDA 会自动合并两个 HPA 的指标，取需要副本数更多的那个值"},
            {"id": "B", "text": "KEDA 会自动删除手动创建的 HPA，用自己创建的 HPA 替代"},
            {"id": "C", "text": "两个 HPA 同时存在，各自独立地修改 Deployment 的 replicas 字段，导致副本数不断震荡"},
            {"id": "D", "text": "Kubernetes API Server 会拒绝创建 ScaledObject，返回冲突错误"}
          ],
          "correctAnswer": "C",
          "explanation": "这是 KEDA 使用中最常见的坑之一。KEDA Operator 会为 ScaledObject 创建一个新的 HPA 对象（名称为 keda-hpa-xxx），但它不会检测或删除已有的手动创建的 HPA。结果是两个 HPA 同时 watch 同一个 Deployment 的 Scale 子资源——手动 HPA 基于 CPU 计算出 3 副本，KEDA HPA 基于 Kafka Lag 计算出 15 副本，两者交替修改 replicas 字段，副本数在两个值之间不断跳变。正确做法是在创建 ScaledObject 之前先删除手动创建的 HPA。A 描述的自动合并机制不存在。D 在没有 Admission Webhook 拦截的情况下不会发生。"
        },
        {
          "id": "k8s-keda-vs-native-hpa-q1-quiz7",
          "question": "对比 KEDA 的 ScaledObject 和 ScaledJob，以下哪个描述最准确？",
          "choices": [
            {"id": "A", "text": "ScaledObject 管理 Deployment/StatefulSet 的副本数适合持续消费型负载，ScaledJob 管理 Kubernetes Job 的创建适合一次性事件处理任务"},
            {"id": "B", "text": "两者功能相同，ScaledJob 只是 ScaledObject 的旧版本命名"},
            {"id": "C", "text": "ScaledObject 只能基于 CPU/内存扩缩，ScaledJob 才能使用外部事件源"},
            {"id": "D", "text": "ScaledObject 管理单个 Pod，ScaledJob 管理 Pod 集群"}
          ],
          "correctAnswer": "A",
          "explanation": "ScaledObject 和 ScaledJob 是 KEDA 的两种核心 CRD，针对不同的工作负载模式设计。ScaledObject 的 scaleTargetRef 指向 Deployment 或 StatefulSet，通过调整 replicas 实现扩缩——适合 Kafka 消费者、RabbitMQ 消费者这类长期运行的服务。ScaledJob 则是根据事件创建 Kubernetes Job——比如每收到一个视频上传事件就创建一个转码 Job，Job 完成后自动清理，maxReplicaCount 控制并发 Job 的上限。B 不正确，两者是独立的 CRD 服务于不同场景。C 完全错误，ScaledObject 同样支持 70+ 种 Scaler。D 混淆了 Pod 和工作负载控制器的概念。"
        },
        {
          "id": "k8s-keda-vs-native-hpa-q1-quiz8",
          "question": "在生产环境中，你的 Kafka 消费者服务使用 KEDA 缩到 0 后，第一条新消息到达时服务需要 45 秒才能启动完成开始处理。业务要求消息处理延迟不超过 10 秒。以下哪种方案最合理？",
          "choices": [
            {"id": "A", "text": "把 cooldownPeriod 设为 5 秒，让 KEDA 更快唤醒 Pod"},
            {"id": "B", "text": "把 idleReplicaCount 设为 1 而不是 0，始终保留一个最小副本来处理零星消息，避免冷启动延迟"},
            {"id": "C", "text": "把 pollingInterval 设为 1 秒，让 KEDA 更频繁地检测新消息"},
            {"id": "D", "text": "在 Kafka 生产者端增加 45 秒的消息发送延迟来匹配 Pod 启动时间"}
          ],
          "correctAnswer": "B",
          "explanation": "冷启动延迟是缩零场景的核心取舍。cooldownPeriod 控制的是「从活跃到缩零前的等待时间」，跟唤醒速度无关（A 错）。pollingInterval 控制的是 KEDA 检查指标的频率，即使 1 秒检查一次，Pod 启动还是需要 45 秒（C 无效）。D 是荒谬的反模式——让上游迁就下游的启动慢问题。正确的做法是承认 45 秒冷启动与 10 秒 SLA 不兼容，把 idleReplicaCount 设为 1 保留一个热副本。这样牺牲了完全缩零的成本节省，但保证了消息处理的时效性——这是生产环境中常见的成本与性能的权衡。"
        },
        {
          "id": "k8s-keda-vs-native-hpa-q1-quiz9",
          "question": "KEDA 的 TriggerAuthentication CRD 的作用是什么？",
          "choices": [
            {"id": "A", "text": "控制哪些用户有权限创建 ScaledObject（RBAC 权限管理）"},
            {"id": "B", "text": "安全地向 KEDA Scaler 传递连接事件源所需的敏感凭据，如 Kafka SASL 密码、RabbitMQ 连接字符串等"},
            {"id": "C", "text": "对 Pod 进行 mTLS 认证以实现零信任网络"},
            {"id": "D", "text": "加密 ScaledObject 的 YAML 配置防止 etcd 中的明文存储"}
          ],
          "correctAnswer": "B",
          "explanation": "TriggerAuthentication 是 KEDA 专门为安全凭据管理设计的 CRD。生产环境的 Kafka 集群通常启用了 SASL/SSL 认证，RabbitMQ 需要连接字符串和密码。如果把这些凭据直接写在 ScaledObject 的 metadata 字段中，它们会以明文形式存储在 etcd 中。TriggerAuthentication 允许你从 Kubernetes Secret、HashiCorp Vault、Azure Key Vault 等安全存储中引用凭据，然后在 ScaledObject 的 trigger 中通过 authenticationRef 引用这个 TriggerAuthentication。A 混淆了 RBAC 和 Scaler 认证。C 是服务网格的功能。D 是 Kubernetes Secret Encryption at Rest 的功能。"
        },
        {
          "id": "k8s-keda-vs-native-hpa-q1-quiz10",
          "question": "以下哪种场景最适合使用原生 HPA 而不是 KEDA？",
          "choices": [
            {"id": "A", "text": "一个 Kafka 消费者服务，需要根据 Consumer Lag 自动扩缩"},
            {"id": "B", "text": "一个计算密集型的 REST API 服务，7×24 运行，请求量与 CPU 利用率正相关"},
            {"id": "C", "text": "一个邮件发送服务，凌晨无流量需要缩到 0 副本节省成本"},
            {"id": "D", "text": "一个批处理任务，需要根据 SQS 队列深度创建一次性 Job"}
          ],
          "correctAnswer": "B",
          "explanation": "原生 HPA 的优势场景是：性能瓶颈在 CPU（请求量与 CPU 利用率线性相关）、服务需要 7×24 运行不需要缩零、不需要对接外部事件源。REST API 服务完美匹配这三个条件——收到更多请求 CPU 就更高，HPA 的 CPU 利用率指标能准确反映负载压力，用原生 HPA 零额外依赖最简洁。A 需要 Kafka Lag 指标，HPA 不内置支持。C 需要缩零能力，HPA 不支持。D 需要创建 Job，HPA 只管 Deployment/StatefulSet 的副本数。引入 KEDA 是有运维成本的——多三个组件要监控和升级——所以能用原生 HPA 解决的场景就不要用 KEDA。"
        }
      ],
      "references": [
        "https://keda.sh/docs/2.16/concepts/",
        "https://keda.sh/docs/2.16/scalers/apache-kafka/",
        "https://keda.sh/docs/2.16/scalers/rabbitmq-queue/",
        "https://kubernetes.io/docs/tasks/run-application/horizontal-pod-autoscale/",
        "https://github.com/kedacore/keda/releases/tag/v2.16.1"
      ]
    }
  ]
}
